vllm_hpu_extension/__init__.py
vllm_hpu_extension/cache_ops.py
vllm_hpu_extension/ops.py
vllm_hpu_extension/rotary_embed.py
vllm_hpu_extension/utils.py
vllm_hpu_extension-0.1.dist-info/LICENSE
vllm_hpu_extension-0.1.dist-info/METADATA
vllm_hpu_extension-0.1.dist-info/WHEEL
vllm_hpu_extension-0.1.dist-info/top_level.txt
vllm_hpu_extension-0.1.dist-info/RECORD
